[
  {
    "username": "markiplier",
    "email": "markiplier@gmail.com",
    "nome": "Mark Fischbach",
    "user_timestamp": "2023-11-28 00:58:41.080"
  },
  {
    "username": "lillysingh",
    "email": "lillysingh@gmail.com",
    "nome": "Lilly Singh",
    "user_timestamp": "2023-11-28 00:58:41.118"
  },
  {
    "username": "jennamarbles",
    "email": "jennamarbles@gmail.com",
    "nome": "Jenna Marbles",
    "user_timestamp": "2023-11-28 00:58:41.129"
  },
  {
    "username": "caseyneistat",
    "email": "caseyneistat@gmail.com",
    "nome": "Casey Neistat",
    "user_timestamp": "2023-11-28 00:58:41.138"
  },
  {
    "username": "pewdiepie",
    "email": "pewds@gmail.com",
    "nome": "Felix Kjellberg",
    "user_timestamp": "2023-11-28 00:58:41.043"
  },
  {
    "username": "phillyd",
    "email": "phillyd@gmail.com",
    "nome": "Philip DeFranco",
    "user_timestamp": "2023-11-28 00:58:41.148"
  },
  {
    "username": "mrbeast",
    "email": "mrbeast@gmail.com",
    "nome": "Jimmy Donaldson",
    "user_timestamp": "2023-11-28 00:58:41.055"
  },
  {
    "username": "lizakoshy",
    "email": "lizakoshy@gmail.com",
    "nome": "Liza Koshy",
    "user_timestamp": "2023-11-28 00:58:41.094"
  },
  {
    "username": "daviddobrik",
    "email": "daviddobrik@gmail.com",
    "nome": "David Dobrik",
    "user_timestamp": "2023-11-28 00:58:41.068"
  },
  {
    "username": "ninja",
    "email": "ninja@gmail.com",
    "nome": "Tyler Blevins",
    "user_timestamp": "2023-11-28 00:58:41.104"
  }
]